rmwatchlater/__init__.py
rmwatchlater/imgs/menue.png
rmwatchlater/imgs/rmlater_de.png
rmwatchlater/localisation.csv
rmwatchlater-2025.1.17.dist-info/LICENSE
rmwatchlater-2025.1.17.dist-info/METADATA
rmwatchlater-2025.1.17.dist-info/WHEEL
rmwatchlater-2025.1.17.dist-info/entry_points.txt
rmwatchlater-2025.1.17.dist-info/RECORD
