Metadata-Version: 2.3
Name: rmwatchlater
Version: 2025.1.17
Summary: 
Author: tct123
Author-email: 42028373+tct123@users.noreply.github.com
Requires-Python: >=3.8,<4.0
Classifier: Programming Language :: Python :: 3
Classifier: Programming Language :: Python :: 3.8
Classifier: Programming Language :: Python :: 3.9
Classifier: Programming Language :: Python :: 3.10
Classifier: Programming Language :: Python :: 3.11
Classifier: Programming Language :: Python :: 3.12
Classifier: Programming Language :: Python :: 3.13
Requires-Dist: mylocale (>=2025.1.15,<2026.0.0)
Requires-Dist: pyautogui (>=0.9.54,<0.10.0)
Project-URL: Repository, https://github.com/tct123/rmwatchlater
